sklearn_porter/Porter.py
sklearn_porter/Template.py
sklearn_porter/__init__.py
sklearn_porter/pypi.json
sklearn_porter/cli/__init__.py
sklearn_porter/cli/__main__.py
sklearn_porter/estimator/__init__.py
sklearn_porter/estimator/classifier/Classifier.py
sklearn_porter/estimator/classifier/__init__.py
sklearn_porter/estimator/classifier/AdaBoostClassifier/__init__.py
sklearn_porter/estimator/classifier/AdaBoostClassifier/templates/c/embedded.class.txt
sklearn_porter/estimator/classifier/AdaBoostClassifier/templates/c/embedded.method.txt
sklearn_porter/estimator/classifier/AdaBoostClassifier/templates/c/embedded.method_calls.txt
sklearn_porter/estimator/classifier/AdaBoostClassifier/templates/c/embedded.tree.txt
sklearn_porter/estimator/classifier/AdaBoostClassifier/templates/java/embedded.class.txt
sklearn_porter/estimator/classifier/AdaBoostClassifier/templates/java/embedded.method.txt
sklearn_porter/estimator/classifier/AdaBoostClassifier/templates/java/embedded.method_calls.txt
sklearn_porter/estimator/classifier/AdaBoostClassifier/templates/java/embedded.tree.txt
sklearn_porter/estimator/classifier/AdaBoostClassifier/templates/java/exported.class.txt
sklearn_porter/estimator/classifier/AdaBoostClassifier/templates/js/embedded.class.txt
sklearn_porter/estimator/classifier/AdaBoostClassifier/templates/js/embedded.method.txt
sklearn_porter/estimator/classifier/AdaBoostClassifier/templates/js/embedded.tree.txt
sklearn_porter/estimator/classifier/AdaBoostClassifier/templates/js/exported.class.txt
sklearn_porter/estimator/classifier/BernoulliNB/__init__.py
sklearn_porter/estimator/classifier/BernoulliNB/templates/java/exported.class.txt
sklearn_porter/estimator/classifier/BernoulliNB/templates/java/separated.class.txt
sklearn_porter/estimator/classifier/BernoulliNB/templates/java/separated.method.predict.txt
sklearn_porter/estimator/classifier/BernoulliNB/templates/js/separated.class.txt
sklearn_porter-0.7.4.dist-info/METADATA
sklearn_porter-0.7.4.dist-info/WHEEL
sklearn_porter-0.7.4.dist-info/entry_points.txt
sklearn_porter-0.7.4.dist-info/license.txt
sklearn_porter-0.7.4.dist-info/top_level.txt
sklearn_porter-0.7.4.dist-info/RECORD
