Metadata-Version: 2.1
Name: sklearn-porter
Version: 0.7.4
Summary: Transpile trained scikit-learn models to C, Java, JavaScript and others.
Home-page: https://github.com/nok/sklearn-porter
Author: Darius Morawiec
Author-email: nok@users.noreply.github.com
License: MIT
Keywords: sklearn,scikit-learn
Platform: UNKNOWN
Classifier: Programming Language :: Python :: 2
Classifier: Programming Language :: Python :: 2.7
Classifier: Programming Language :: Python :: 3.4
Classifier: Programming Language :: Python :: 3.5
Classifier: Programming Language :: Python :: 3.6
Classifier: Programming Language :: Python :: 3.7
Requires-Dist: six
Requires-Dist: scikit-learn (>=0.14.1)
